cybotrade_indicators.cpython-311-aarch64-linux-gnu.so
cybotrade_indicators-0.0.7.dist-info/LICENSE
cybotrade_indicators-0.0.7.dist-info/METADATA
cybotrade_indicators-0.0.7.dist-info/RECORD
cybotrade_indicators-0.0.7.dist-info/WHEEL
cybotrade_indicators-0.0.7.dist-info/top_level.txt
cybotrade_indicators-0.0.7.dist-info/AUTHORS
cybotrade_indicators/indicators.pxd
cybotrade_indicators/__init__.c
cybotrade_indicators/py.typed
cybotrade_indicators/__init__.pyx
cybotrade_indicators/__init__.pyi
