Metadata-Version: 2.1
Name: cybotrade-indicators
Version: 0.0.7
Summary: This library provides a set of technical analysis indicators that can be used to craft trading strategies.
Author-email: Marcus Lee <marcuslee@balaenaquant.com>, Lee Ze Lim <zelim@balaenaquant.com>
Project-URL: Homepage, https://app.cybotrade.rs
Project-URL: Documentation, https://docs.cybotrade.rs
Project-URL: Repository, https://github.com/cybotrade/cybotrade-indicators
Classifier: Programming Language :: C
Classifier: Programming Language :: Python :: 3.11
Classifier: Typing :: Typed
Requires-Python: >=3.11
License-File: LICENSE
License-File: AUTHORS
Requires-Dist: numpy >=1.25.0
Requires-Dist: nptyping >=2.5.0
